canarypy/__init__.py
canarypy/alembic.ini
canarypy/client.py
canarypy/config.py
canarypy/api/__init__.py
canarypy/api/config.py
canarypy/api/main.py
canarypy/api/run.py
canarypy/api/db/__init__.py
canarypy/api/db/base.py
canarypy/api/dependencies/__init__.py
canarypy/api/dependencies/db.py
canarypy/api/models/__init__.py
canarypy/api/models/product.py
canarypy/api/models/release.py
canarypy/api/models/signal.py
canarypy/api/routes/__init__.py
canarypy/api/routes/product.py
canarypy/api/routes/release.py
canarypy/api/routes/signal.py
canarypy/api/schemas/__init__.py
canarypy/api/schemas/httperror.py
canarypy/api/schemas/product.py
canarypy/api/schemas/release.py
canarypy/api/schemas/signal.py
canarypy/api/services/__init__.py
canarypy/api/services/product.py
canarypy/api/services/release.py
canarypy/api/services/signal.py
canarypy/cli/__init__.py
canarypy/cli/main.py
canarypy/cli/services/__init__.py
canarypy/cli/services/product.py
canarypy/cli/services/release.py
canarypy/cli/services/signal.py
canarypy/migrations/README
canarypy/migrations/env.py
canarypy/migrations/script.py.mako
canarypy/migrations/versions/1c26034449b9_add_band_number.py
canarypy/migrations/versions/33873c5a7bbe_change_canary_period_type.py
canarypy/migrations/versions/4a95c3cf7adc_initial_tables.py
canarypy/migrations/versions/5a588045e274_add_release_date.py
canarypy/migrations/versions/652e9c47c653_add_is_canary_to_signal.py
canarypy/migrations/versions/67c9708da025_add_release_canary_band_table.py
canarypy/migrations/versions/738957fcc3bc_add_signal_period_column.py
canarypy/migrations/versions/84a61d063ad6_add_release_status_columns.py
canarypy/migrations/versions/9261790e46ac_change_canary_period_type.py
canarypy/migrations/versions/9505cfab1f85_refactor_bands.py
canarypy/migrations/versions/9dbfd3ac874b_add_release_period_columns.py
canarypy/migrations/versions/aebc398fc592_change_mandatory_field.py
canarypy/migrations/versions/d1b816f53004_change_product_name.py
canarypy-0.0.14.dist-info/LICENSE
canarypy-0.0.14.dist-info/METADATA
canarypy-0.0.14.dist-info/WHEEL
canarypy-0.0.14.dist-info/entry_points.txt
canarypy-0.0.14.dist-info/top_level.txt
canarypy-0.0.14.dist-info/RECORD
