Metadata-Version: 2.1
Name: canarypy
Version: 0.0.14
Summary: CanaryPy - A light and powerful canary release for Data Pipelines
Home-page: https://github.com/thcidale0808/canarypy
Author: Thiago Assumpcao
Author-email: thcidale@gmail.com
License: UNKNOWN
Project-URL: Bug Reports, https://github.com/thcidale0808/canarypy/issues
Project-URL: Source, https://github.com/thcidale0808/canarypy/
Platform: UNKNOWN
Classifier: Development Status :: 3 - Alpha
Classifier: Intended Audience :: Developers
Classifier: Topic :: Software Development :: Build Tools
Classifier: License :: OSI Approved :: MIT License
Classifier: Programming Language :: Python :: 3.8
Classifier: Programming Language :: Python :: 3.9
Classifier: Programming Language :: Python :: 3.10
Classifier: Programming Language :: Python :: 3.11
Requires-Python: >=3.8
Requires-Dist: fastapi (~=0.75.2)
Requires-Dist: uvicorn (~=0.17.6)
Requires-Dist: psycopg2-binary (~=2.9.0)
Requires-Dist: SQLAlchemy (<2.0.0,>=1.4.0)
Requires-Dist: python-jose[cryptography] (<3.4.0,>=3.3.0)
Requires-Dist: requests (<2.28.0,>=2.27.0)
Requires-Dist: aiofiles (<0.9.0,>=0.8.0)
Requires-Dist: click (~=8.1.2)
Requires-Dist: alembic
Requires-Dist: InquirerPy
Requires-Dist: pywebio
Requires-Dist: plotly
Requires-Dist: pandas
Requires-Dist: streamlit
